{
  "college_name": "Butte",
  "total_enrollments": 34780,
  "top4_codes": {
    "0502": {
      "name": "Accounting",
      "enrollment": 716,
      "grades": {
        "W": 0.1899,
        "A": 0.3059,
        "B": 0.1718,
        "C": 0.1173,
        "D": 0.0461,
        "F": 0.169
      }
    },
    "2105": {
      "name": "Administration of Justice",
      "enrollment": 836,
      "grades": {
        "W": 0.1124,
        "A": 0.2871,
        "B": 0.2045,
        "C": 0.1148,
        "D": 0.0395,
        "F": 0.1136,
        "P": 0.128
      }
    },
    "0116": {
      "name": "Agricultural Power Equipment Technology",
      "enrollment": 121,
      "grades": {
        "W": 0.0414,
        "A": 0.4463,
        "B": 0.2645,
        "C": 0.1653,
        "D": 0.0165,
        "F": 0.0661
      }
    },
    "0112": {
      "name": "Agriculture Business, Sales and Service",
      "enrollment": 245,
      "grades": {
        "W": 0.0857,
        "A": 0.4531,
        "B": 0.2163,
        "C": 0.1429,
        "D": 0.0367,
        "F": 0.0653
      }
    },
    "0101": {
      "name": "Agriculture Technology and Sciences, General",
      "enrollment": 48,
      "grades": {
        "A": 0.4167,
        "B": 0.1458,
        "C": 0.2083,
        "D": 0.0208,
        "F": 0.0833,
        "W": 0.125
      }
    },
    "0410": {
      "name": "Anatomy and Physiology",
      "enrollment": 665,
      "grades": {
        "W": 0.1293,
        "A": 0.3308,
        "B": 0.2105,
        "C": 0.1549,
        "D": 0.0602,
        "F": 0.1143
      }
    },
    "0102": {
      "name": "Animal Science",
      "enrollment": 31,
      "grades": {
        "A": 0.3871,
        "B": 0.3226,
        "C": 0.0645,
        "F": 0.0645,
        "W": 0.1613
      }
    },
    "2202": {
      "name": "Anthropology",
      "enrollment": 577,
      "grades": {
        "W": 0.0805,
        "A": 0.4396,
        "B": 0.1611,
        "C": 0.1261,
        "D": 0.0473,
        "F": 0.1436,
        "P": 0.0017
      }
    },
    "1012": {
      "name": "Applied Photography",
      "enrollment": 9,
      "grades": {
        "A": 0.3333,
        "B": 0.5556,
        "C": 0.1111
      }
    },
    "1002": {
      "name": "Art",
      "enrollment": 448,
      "grades": {
        "W": 0.1227,
        "A": 0.5692,
        "B": 0.1295,
        "C": 0.0759,
        "D": 0.0179,
        "F": 0.0781,
        "P": 0.0067
      }
    },
    "1911": {
      "name": "Astronomy",
      "enrollment": 115,
      "grades": {
        "W": 0.1739,
        "A": 0.2696,
        "B": 0.1652,
        "C": 0.1304,
        "D": 0.0435,
        "F": 0.2087,
        "P": 0.0087
      }
    },
    "0948": {
      "name": "Automotive Technology",
      "enrollment": 432,
      "grades": {
        "W": 0.0467,
        "A": 0.2804,
        "B": 0.2757,
        "C": 0.2593,
        "D": 0.0257,
        "F": 0.0677,
        "P": 0.0444
      }
    },
    "0401": {
      "name": "Biology, General",
      "enrollment": 436,
      "grades": {
        "W": 0.1376,
        "A": 0.4289,
        "B": 0.1858,
        "C": 0.117,
        "D": 0.0275,
        "F": 0.1009,
        "P": 0.0023
      }
    },
    "0501": {
      "name": "Business and Commerce, General",
      "enrollment": 690,
      "grades": {
        "W": 0.1449,
        "A": 0.313,
        "B": 0.2174,
        "C": 0.1275,
        "D": 0.0681,
        "F": 0.129
      }
    },
    "0506": {
      "name": "Business Management",
      "enrollment": 219,
      "grades": {
        "W": 0.1096,
        "A": 0.3699,
        "B": 0.21,
        "C": 0.1507,
        "D": 0.0594,
        "F": 0.1005
      }
    },
    "1905": {
      "name": "Chemistry, General",
      "enrollment": 704,
      "grades": {
        "W": 0.1264,
        "A": 0.2798,
        "B": 0.2983,
        "C": 0.1832,
        "D": 0.0511,
        "F": 0.0611
      }
    },
    "1305": {
      "name": "Child Development/Early Care and Education",
      "enrollment": 1450,
      "grades": {
        "W": 0.0973,
        "A": 0.4569,
        "B": 0.1808,
        "C": 0.107,
        "D": 0.0317,
        "F": 0.1263
      }
    },
    "0957": {
      "name": "Civil and Construction Management Technology",
      "enrollment": 100,
      "grades": {
        "A": 0.27,
        "B": 0.31,
        "C": 0.23,
        "D": 0.07,
        "F": 0.09,
        "W": 0.03
      }
    },
    "1005": {
      "name": "Commercial Music",
      "enrollment": 63,
      "grades": {
        "W": 0.1904,
        "A": 0.508,
        "B": 0.0794,
        "C": 0.0952,
        "D": 0.0635,
        "F": 0.0635
      }
    },
    "1503": {
      "name": "Comparative Literature",
      "enrollment": 91,
      "grades": {
        "W": 0.1429,
        "A": 0.4615,
        "B": 0.1648,
        "C": 0.044,
        "D": 0.022,
        "F": 0.1648
      }
    },
    "0702": {
      "name": "Computer Information Systems",
      "enrollment": 39,
      "grades": {
        "W": 0.1818,
        "A": 0.4545,
        "B": 0.1212,
        "F": 0.1212,
        "P": 0.1212
      }
    },
    "0708": {
      "name": "Computer Infrastructure and Support",
      "enrollment": 112,
      "grades": {
        "A": 0.4375,
        "B": 0.2589,
        "C": 0.0982,
        "D": 0.0179,
        "F": 0.1071,
        "W": 0.0804
      }
    },
    "0706": {
      "name": "Computer Science (Transfer)",
      "enrollment": 117,
      "grades": {
        "W": 0.2931,
        "A": 0.2414,
        "B": 0.1207,
        "C": 0.1121,
        "D": 0.0172,
        "F": 0.2155
      }
    },
    "0707": {
      "name": "Computer Software Development",
      "enrollment": 211,
      "grades": {
        "W": 0.1991,
        "A": 0.3128,
        "B": 0.1564,
        "C": 0.0995,
        "D": 0.0616,
        "F": 0.1706
      }
    },
    "0952": {
      "name": "Construction Crafts Technology",
      "enrollment": 301,
      "grades": {
        "W": 0.0465,
        "A": 0.4053,
        "B": 0.2458,
        "C": 0.1628,
        "D": 0.0233,
        "F": 0.1163
      }
    },
    "3007": {
      "name": "Cosmetology and Barbering",
      "enrollment": 285,
      "grades": {
        "W": 0.0567,
        "A": 0.5745,
        "B": 0.2624,
        "C": 0.0957,
        "F": 0.0106
      }
    },
    "1507": {
      "name": "Creative Writing",
      "enrollment": 75,
      "grades": {
        "A": 0.44,
        "B": 0.1467,
        "C": 0.1067,
        "D": 0.04,
        "F": 0.1333,
        "W": 0.1333
      }
    },
    "0947": {
      "name": "Diesel Technology",
      "enrollment": 126,
      "grades": {
        "W": 0.1111,
        "A": 0.4127,
        "B": 0.254,
        "C": 0.1667,
        "D": 0.0238,
        "F": 0.0317
      }
    },
    "0614": {
      "name": "Digital Media",
      "enrollment": 139,
      "grades": {
        "W": 0.0288,
        "A": 0.5251,
        "B": 0.1871,
        "C": 0.1367,
        "D": 0.036,
        "F": 0.0863
      }
    },
    "0953": {
      "name": "Drafting Technology",
      "enrollment": 148,
      "grades": {
        "W": 0.1486,
        "A": 0.3986,
        "B": 0.1149,
        "C": 0.0946,
        "D": 0.0135,
        "F": 0.2297
      }
    },
    "1007": {
      "name": "Dramatic Arts",
      "enrollment": 141,
      "grades": {
        "W": 0.0993,
        "A": 0.6454,
        "B": 0.078,
        "C": 0.0851,
        "D": 0.0213,
        "F": 0.0709
      }
    },
    "1930": {
      "name": "Earth Science",
      "enrollment": 23,
      "grades": {
        "A": 0.3913,
        "B": 0.2174,
        "C": 0.1304,
        "D": 0.0435,
        "F": 0.087,
        "W": 0.1304
      }
    },
    "2204": {
      "name": "Economics",
      "enrollment": 522,
      "grades": {
        "W": 0.1035,
        "A": 0.3008,
        "B": 0.295,
        "C": 0.1475,
        "D": 0.0632,
        "F": 0.09
      }
    },
    "0801": {
      "name": "Education, General",
      "enrollment": 81,
      "grades": {
        "W": 0.0499,
        "A": 0.3375,
        "B": 0.1625,
        "C": 0.075,
        "D": 0.025,
        "F": 0.0625,
        "P": 0.2876
      }
    },
    "1250": {
      "name": "Emergency Medical Services",
      "enrollment": 166,
      "grades": {
        "A": 0.3976,
        "B": 0.3494,
        "C": 0.2108,
        "D": 0.012,
        "F": 0.0241,
        "W": 0.006
      }
    },
    "0924": {
      "name": "Engineering Technology, General",
      "enrollment": 22,
      "grades": {
        "A": 0.5455,
        "B": 0.1818,
        "C": 0.0909,
        "D": 0.0909,
        "F": 0.0909
      }
    },
    "0901": {
      "name": "Engineering, General",
      "enrollment": 74,
      "grades": {
        "A": 0.6216,
        "B": 0.1757,
        "C": 0.1216,
        "D": 0.0541,
        "F": 0.0135,
        "W": 0.0135
      }
    },
    "1501": {
      "name": "English",
      "enrollment": 2689,
      "grades": {
        "W": 0.1248,
        "A": 0.364,
        "B": 0.1966,
        "C": 0.1446,
        "D": 0.0482,
        "F": 0.1218
      }
    },
    "0946": {
      "name": "Environmental Control Technology (HVAC)",
      "enrollment": 72,
      "grades": {
        "A": 0.75,
        "B": 0.2083,
        "F": 0.0417
      }
    },
    "2203": {
      "name": "Ethnic Studies",
      "enrollment": 1231,
      "grades": {
        "W": 0.1007,
        "A": 0.4062,
        "B": 0.2015,
        "C": 0.1503,
        "D": 0.0414,
        "F": 0.0983,
        "P": 0.0016
      }
    },
    "1303": {
      "name": "Fashion",
      "enrollment": 88,
      "grades": {
        "A": 0.3409,
        "B": 0.1591,
        "C": 0.0682,
        "D": 0.0455,
        "F": 0.2841,
        "W": 0.1023
      }
    },
    "0612": {
      "name": "Film Studies",
      "enrollment": 120,
      "grades": {
        "A": 0.525,
        "B": 0.2,
        "C": 0.075,
        "D": 0.0417,
        "F": 0.05,
        "W": 0.1083
      }
    },
    "1001": {
      "name": "Fine Arts, General",
      "enrollment": 837,
      "grades": {
        "W": 0.1088,
        "A": 0.5423,
        "B": 0.1673,
        "C": 0.0836,
        "D": 0.0227,
        "F": 0.0753
      }
    },
    "2133": {
      "name": "Fire Technology",
      "enrollment": 293,
      "grades": {
        "A": 0.3965,
        "B": 0.2517,
        "C": 0.1793,
        "D": 0.0207,
        "F": 0.0966,
        "W": 0.0552
      }
    },
    "0114": {
      "name": "Forestry",
      "enrollment": 23,
      "grades": {
        "A": 0.3913,
        "B": 0.3043,
        "C": 0.1739,
        "D": 0.0435,
        "F": 0.0435,
        "W": 0.0435
      }
    },
    "4930": {
      "name": "General Studies",
      "enrollment": 297,
      "grades": {
        "W": 0.0811,
        "A": 0.4459,
        "B": 0.169,
        "C": 0.1182,
        "D": 0.0541,
        "F": 0.1317
      }
    },
    "2206": {
      "name": "Geography",
      "enrollment": 236,
      "grades": {
        "W": 0.1271,
        "A": 0.2415,
        "B": 0.2458,
        "C": 0.1949,
        "D": 0.0424,
        "F": 0.1483
      }
    },
    "1914": {
      "name": "Geology",
      "enrollment": 56,
      "grades": {
        "W": 0.1608,
        "A": 0.375,
        "B": 0.1964,
        "C": 0.125,
        "D": 0.0714,
        "F": 0.0714
      }
    },
    "1103": {
      "name": "German",
      "enrollment": 24,
      "grades": {
        "W": 0.375,
        "A": 0.1667,
        "B": 0.25,
        "C": 0.1667,
        "F": 0.0417
      }
    },
    "1030": {
      "name": "Graphic Art and Design",
      "enrollment": 34,
      "grades": {
        "A": 0.4412,
        "B": 0.2647,
        "C": 0.1176,
        "D": 0.0294,
        "W": 0.1471
      }
    },
    "0837": {
      "name": "Health Education",
      "enrollment": 195,
      "grades": {
        "A": 0.5026,
        "B": 0.2051,
        "C": 0.0821,
        "D": 0.041,
        "F": 0.0615,
        "W": 0.1077
      }
    },
    "1223": {
      "name": "Health Information Technology",
      "enrollment": 182,
      "grades": {
        "A": 0.489,
        "B": 0.1868,
        "C": 0.0934,
        "D": 0.0055,
        "F": 0.1374,
        "W": 0.0879
      }
    },
    "1201": {
      "name": "Health Occupations, General",
      "enrollment": 130,
      "grades": {
        "W": 0.0692,
        "A": 0.6308,
        "B": 0.1385,
        "C": 0.0538,
        "D": 0.0077,
        "F": 0.1
      }
    },
    "2205": {
      "name": "History",
      "enrollment": 1233,
      "grades": {
        "W": 0.0902,
        "A": 0.3618,
        "B": 0.2114,
        "C": 0.1521,
        "D": 0.0528,
        "F": 0.1317
      }
    },
    "0109": {
      "name": "Horticulture",
      "enrollment": 74,
      "grades": {
        "W": 0.1622,
        "A": 0.4595,
        "B": 0.2297,
        "C": 0.1351,
        "D": 0.0135
      }
    },
    "2104": {
      "name": "Human Services",
      "enrollment": 35,
      "grades": {
        "W": 0.0857,
        "A": 0.5715,
        "B": 0.1143,
        "C": 0.0571,
        "D": 0.0571,
        "F": 0.1143
      }
    },
    "0701": {
      "name": "Information Technology, General",
      "enrollment": 16,
      "grades": {
        "A": 0.3125,
        "B": 0.375,
        "F": 0.25,
        "W": 0.0625
      }
    },
    "1108": {
      "name": "Japanese",
      "enrollment": 60,
      "grades": {
        "W": 0.1667,
        "A": 0.2333,
        "B": 0.2167,
        "C": 0.1333,
        "D": 0.0833,
        "F": 0.1667
      }
    },
    "0602": {
      "name": "Journalism",
      "enrollment": 21,
      "grades": {
        "A": 0.3333,
        "B": 0.2381,
        "C": 0.0476,
        "F": 0.0952,
        "W": 0.2857
      }
    },
    "1270": {
      "name": "Kinesiology",
      "enrollment": 159,
      "grades": {
        "A": 0.3333,
        "B": 0.2579,
        "C": 0.1698,
        "D": 0.0755,
        "F": 0.0943,
        "W": 0.0692
      }
    },
    "0956": {
      "name": "Manufacturing and Industrial Technology",
      "enrollment": 850,
      "grades": {
        "W": 0.0486,
        "A": 0.1382,
        "B": 0.2615,
        "C": 0.2104,
        "D": 0.0449,
        "F": 0.0747,
        "P": 0.2216
      }
    },
    "0509": {
      "name": "Marketing and Distribution",
      "enrollment": 115,
      "grades": {
        "W": 0.3044,
        "A": 0.2174,
        "B": 0.1652,
        "C": 0.1565,
        "D": 0.0522,
        "F": 0.1043
      }
    },
    "0610": {
      "name": "Mass Communications",
      "enrollment": 59,
      "grades": {
        "A": 0.2542,
        "B": 0.3051,
        "C": 0.0847,
        "D": 0.0339,
        "F": 0.1186,
        "W": 0.2034
      }
    },
    "1701": {
      "name": "Mathematics, General",
      "enrollment": 2157,
      "grades": {
        "W": 0.1308,
        "A": 0.2639,
        "B": 0.2203,
        "C": 0.1693,
        "D": 0.0519,
        "F": 0.1633,
        "P": 0.0005
      }
    },
    "0403": {
      "name": "Microbiology",
      "enrollment": 167,
      "grades": {
        "W": 0.0482,
        "A": 0.2831,
        "B": 0.3012,
        "C": 0.2891,
        "D": 0.0542,
        "F": 0.0241
      }
    },
    "1004": {
      "name": "Music",
      "enrollment": 1234,
      "grades": {
        "W": 0.1103,
        "A": 0.4866,
        "B": 0.1573,
        "C": 0.0917,
        "D": 0.0276,
        "F": 0.1265
      }
    },
    "0408": {
      "name": "Natural History",
      "enrollment": 34,
      "grades": {
        "W": 0.0882,
        "A": 0.4118,
        "B": 0.1471,
        "C": 0.1471,
        "D": 0.0294,
        "F": 0.1765
      }
    },
    "0115": {
      "name": "Natural Resources",
      "enrollment": 49,
      "grades": {
        "W": 0.0408,
        "A": 0.5919,
        "B": 0.2041,
        "C": 0.102,
        "F": 0.0612
      }
    },
    "1230": {
      "name": "Nursing",
      "enrollment": 1746,
      "grades": {
        "A": 0.4651,
        "B": 0.2228,
        "C": 0.0281,
        "F": 0.0011,
        "P": 0.2795,
        "W": 0.0034
      }
    },
    "1306": {
      "name": "Nutrition, Foods, and Culinary Arts",
      "enrollment": 742,
      "grades": {
        "W": 0.1079,
        "A": 0.4629,
        "B": 0.1484,
        "C": 0.112,
        "D": 0.0567,
        "F": 0.112
      }
    },
    "0514": {
      "name": "Office Technology/Office Computer Applications",
      "enrollment": 795,
      "grades": {
        "W": 0.1295,
        "A": 0.5296,
        "B": 0.117,
        "C": 0.073,
        "D": 0.0226,
        "F": 0.1283
      }
    },
    "0499": {
      "name": "Other Biological Sciences",
      "enrollment": 125,
      "grades": {
        "W": 0.088,
        "A": 0.32,
        "B": 0.192,
        "C": 0.224,
        "D": 0.064,
        "F": 0.112
      }
    },
    "1251": {
      "name": "Paramedic",
      "enrollment": 24,
      "grades": {
        "A": 0.6667,
        "B": 0.2083,
        "F": 0.0417,
        "W": 0.0833
      }
    },
    "1509": {
      "name": "Philosophy",
      "enrollment": 235,
      "grades": {
        "W": 0.0766,
        "A": 0.383,
        "B": 0.2298,
        "C": 0.1745,
        "D": 0.0553,
        "F": 0.0809
      }
    },
    "1011": {
      "name": "Photography",
      "enrollment": 130,
      "grades": {
        "A": 0.4923,
        "B": 0.1385,
        "C": 0.0692,
        "D": 0.0231,
        "F": 0.0846,
        "W": 0.1923
      }
    },
    "0835": {
      "name": "Physical Education",
      "enrollment": 1870,
      "grades": {
        "W": 0.0718,
        "A": 0.7203,
        "B": 0.0728,
        "C": 0.0507,
        "D": 0.0182,
        "F": 0.0425,
        "P": 0.0237
      }
    },
    "1901": {
      "name": "Physical Sciences, General",
      "enrollment": 255,
      "grades": {
        "W": 0.0549,
        "A": 0.3451,
        "B": 0.2588,
        "C": 0.2,
        "D": 0.0549,
        "F": 0.0863
      }
    },
    "1902": {
      "name": "Physics, General",
      "enrollment": 246,
      "grades": {
        "A": 0.2398,
        "B": 0.2358,
        "C": 0.252,
        "D": 0.0691,
        "F": 0.1057,
        "W": 0.0976
      }
    },
    "0103": {
      "name": "Plant Science",
      "enrollment": 149,
      "grades": {
        "W": 0.1689,
        "A": 0.2297,
        "B": 0.1959,
        "C": 0.1824,
        "D": 0.0406,
        "F": 0.1824
      }
    },
    "2207": {
      "name": "Political Science",
      "enrollment": 740,
      "grades": {
        "W": 0.0393,
        "A": 0.4533,
        "B": 0.2003,
        "C": 0.1164,
        "D": 0.0623,
        "F": 0.1259,
        "P": 0.0027
      }
    },
    "2001": {
      "name": "Psychology, General",
      "enrollment": 1553,
      "grades": {
        "W": 0.0573,
        "A": 0.5139,
        "B": 0.1938,
        "C": 0.1075,
        "D": 0.0406,
        "F": 0.0869
      }
    },
    "0604": {
      "name": "Radio and Television",
      "enrollment": 66,
      "grades": {
        "W": 0.1516,
        "A": 0.4697,
        "B": 0.1212,
        "C": 0.0909,
        "F": 0.1667
      }
    },
    "0511": {
      "name": "Real Estate",
      "enrollment": 151,
      "grades": {
        "A": 0.457,
        "B": 0.2053,
        "C": 0.0927,
        "D": 0.0199,
        "F": 0.1523,
        "W": 0.0728
      }
    },
    "1210": {
      "name": "Respiratory Care/Therapy",
      "enrollment": 130,
      "grades": {
        "A": 0.6923,
        "B": 0.2077,
        "C": 0.0231,
        "F": 0.0615,
        "W": 0.0154
      }
    },
    "0850": {
      "name": "Sign Language",
      "enrollment": 171,
      "grades": {
        "W": 0.193,
        "A": 0.269,
        "B": 0.1637,
        "C": 0.1345,
        "D": 0.0468,
        "F": 0.193
      }
    },
    "2201": {
      "name": "Social Sciences, General",
      "enrollment": 131,
      "grades": {
        "A": 0.3893,
        "B": 0.1985,
        "C": 0.145,
        "D": 0.0458,
        "F": 0.1527,
        "P": 0.0076,
        "W": 0.0611
      }
    },
    "2208": {
      "name": "Sociology",
      "enrollment": 535,
      "grades": {
        "W": 0.0598,
        "A": 0.4636,
        "B": 0.1832,
        "C": 0.0935,
        "D": 0.0486,
        "F": 0.1514
      }
    },
    "1105": {
      "name": "Spanish",
      "enrollment": 259,
      "grades": {
        "W": 0.1042,
        "A": 0.5136,
        "B": 0.1544,
        "C": 0.0579,
        "D": 0.0386,
        "F": 0.1274,
        "P": 0.0039
      }
    },
    "0809": {
      "name": "Special Education",
      "enrollment": 4,
      "grades": {
        "A": 1.0
      }
    },
    "1506": {
      "name": "Speech Communication",
      "enrollment": 1373,
      "grades": {
        "W": 0.1019,
        "A": 0.3853,
        "B": 0.2251,
        "C": 0.1544,
        "D": 0.0233,
        "F": 0.1092,
        "P": 0.0007
      }
    },
    "1006": {
      "name": "Technical Theater",
      "enrollment": 2,
      "grades": {
        "A": 0.5,
        "B": 0.5
      }
    }
  }
}